README.md
setup.py
PythonDm32/__init__.py
PythonDm32/pydm.py
PythonDm32.egg-info/PKG-INFO
PythonDm32.egg-info/SOURCES.txt
PythonDm32.egg-info/dependency_links.txt
PythonDm32.egg-info/requires.txt
PythonDm32.egg-info/top_level.txt
PythonDm32/dm/DmReg.dll
PythonDm32/dm/RegDll.dll
PythonDm32/dm/dm.dll
PythonDm32/dm/dm3.1233.dll
PythonDm32/dm/xx.dat
PythonDm32/dm/从系统里卸载大漠插件.bat
PythonDm32/dm/大漠接口说明v3.1233.chm
PythonDm32/dm/大漠接口说明v7.2450.chm
PythonDm32/dm/注册大漠插件到系统.bat
tests/__init__.py
tests/test_dm_reg.py
tools/__init__.py