Metadata-Version: 2.1
Name: PythonDm32
Version: 1.1.0
Summary: dm.dll user to python
Home-page: UNKNOWN
Author: 孙亮
Author-email: 3028772928@qq.com
License: UNKNOWN
Platform: UNKNOWN
Requires-Python: >=3.6
